{"minecraft:orange_carpet":{"nbt":{},"stacks":[{"details":{"tags":{"minecraft:wool_carpets":true,"chipped:orange_carpet":true,"c:dyed/orange":true,"c:dyed":true,"minecraft:dampens_vibrations":true},"mapColour":14188339,"name":"minecraft:orange_carpet","itemGroups":[{"id":"minecraft:colored_blocks","displayName":"Colored Blocks"}],"count":64,"mapColor":14188339,"maxCount":64,"displayName":"Orange Carpet"},"source":"minecraft:barrel_6","slot":3}]},"empty_slot":{"nbt":{},"stacks":[{"details":{"count":0,"maxCount":0},"source":"minecraft:barrel_6","slot":1},{"details":{"count":0,"maxCount":0},"source":"minecraft:barrel_6","slot":5},{"details":{"count":0,"maxCount":0},"source":"minecraft:barrel_6","slot":6},{"details":{"count":0,"maxCount":0},"source":"minecraft:barrel_6","slot":7},{"details":{"count":0,"maxCount":0},"source":"minecraft:barrel_6","slot":8},{"details":{"count":0,"maxCount":0},"source":"minecraft:barrel_6","slot":9},{"details":{"count":0,"maxCount":0},"source":"minecraft:barrel_6","slot":10},{"details":{"count":0,"maxCount":0},"source":"minecraft:barrel_6","slot":11},{"details":{"count":0,"maxCount":0},"source":"minecraft:barrel_6","slot":12},{"details":{"count":0,"maxCount":0},"source":"minecraft:barrel_6","slot":13},{"details":{"count":0,"maxCount":0},"source":"minecraft:barrel_6","slot":14},{"details":{"count":0,"maxCount":0},"source":"minecraft:barrel_6","slot":15},{"details":{"count":0,"maxCount":0},"source":"minecraft:barrel_6","slot":16},{"details":{"count":0,"maxCount":0},"source":"minecraft:barrel_6","slot":17},{"details":{"count":0,"maxCount":0},"source":"minecraft:barrel_6","slot":18},{"details":{"count":0,"maxCount":0},"source":"minecraft:barrel_6","slot":19},{"details":{"count":0,"maxCount":0},"source":"minecraft:barrel_6","slot":20},{"details":{"count":0,"maxCount":0},"source":"minecraft:barrel_6","slot":21},{"details":{"count":0,"maxCount":0},"source":"minecraft:barrel_6","slot":22},{"details":{"count":0,"maxCount":0},"source":"minecraft:barrel_6","slot":23},{"details":{"count":0,"maxCount":0},"source":"minecraft:barrel_6","slot":24},{"details":{"count":0,"maxCount":0},"source":"minecraft:barrel_6","slot":25},{"details":{"count":0,"maxCount":0},"source":"minecraft:barrel_6","slot":26},{"details":{"count":0,"maxCount":0},"source":"minecraft:barrel_6","slot":27},{"details":{"count":0,"maxCount":0},"source":"minecraft:barrel_7","slot":1},{"details":{"count":0,"maxCount":0},"source":"minecraft:barrel_7","slot":2},{"details":{"count":0,"maxCount":0},"source":"minecraft:barrel_7","slot":3},{"details":{"count":0,"maxCount":0},"source":"minecraft:barrel_7","slot":4},{"details":{"count":0,"maxCount":0},"source":"minecraft:barrel_7","slot":5},{"details":{"count":0,"maxCount":0},"source":"minecraft:barrel_7","slot":6},{"details":{"count":0,"maxCount":0},"source":"minecraft:barrel_7","slot":7},{"details":{"count":0,"maxCount":0},"source":"minecraft:barrel_7","slot":8},{"details":{"count":0,"maxCount":0},"source":"minecraft:barrel_7","slot":9},{"details":{"count":0,"maxCount":0},"source":"minecraft:barrel_7","slot":10},{"details":{"count":0,"maxCount":0},"source":"minecraft:barrel_7","slot":11},{"details":{"count":0,"maxCount":0},"source":"minecraft:barrel_7","slot":12},{"details":{"count":0,"maxCount":0},"source":"minecraft:barrel_7","slot":13},{"details":{"count":0,"maxCount":0},"source":"minecraft:barrel_7","slot":14},{"details":{"count":0,"maxCount":0},"source":"minecraft:barrel_7","slot":15},{"details":{"count":0,"maxCount":0},"source":"minecraft:barrel_7","slot":16},{"details":{"count":0,"maxCount":0},"source":"minecraft:barrel_7","slot":17},{"details":{"count":0,"maxCount":0},"source":"minecraft:barrel_7","slot":18},{"details":{"count":0,"maxCount":0},"source":"minecraft:barrel_7","slot":19},{"details":{"count":0,"maxCount":0},"source":"minecraft:barrel_7","slot":20},{"details":{"count":0,"maxCount":0},"source":"minecraft:barrel_7","slot":21},{"details":{"count":0,"maxCount":0},"source":"minecraft:barrel_7","slot":22},{"details":{"count":0,"maxCount":0},"source":"minecraft:barrel_7","slot":23},{"details":{"count":0,"maxCount":0},"source":"minecraft:barrel_7","slot":24},{"details":{"count":0,"maxCount":0},"source":"minecraft:barrel_7","slot":25},{"details":{"count":0,"maxCount":0},"source":"minecraft:barrel_7","slot":26},{"details":{"count":0,"maxCount":0},"source":"minecraft:barrel_7","slot":27},{"details":{"count":0,"maxCount":0},"source":"minecraft:barrel_4","slot":1},{"details":{"count":0,"maxCount":0},"source":"minecraft:barrel_4","slot":2},{"details":{"count":0,"maxCount":0},"source":"minecraft:barrel_4","slot":3},{"details":{"count":0,"maxCount":0},"source":"minecraft:barrel_4","slot":4},{"details":{"count":0,"maxCount":0},"source":"minecraft:barrel_4","slot":5},{"details":{"count":0,"maxCount":0},"source":"minecraft:barrel_4","slot":6},{"details":{"count":0,"maxCount":0},"source":"minecraft:barrel_4","slot":7},{"details":{"count":0,"maxCount":0},"source":"minecraft:barrel_4","slot":8},{"details":{"count":0,"maxCount":0},"source":"minecraft:barrel_4","slot":9},{"details":{"count":0,"maxCount":0},"source":"minecraft:barrel_4","slot":10},{"details":{"count":0,"maxCount":0},"source":"minecraft:barrel_4","slot":11},{"details":{"count":0,"maxCount":0},"source":"minecraft:barrel_4","slot":12},{"details":{"count":0,"maxCount":0},"source":"minecraft:barrel_4","slot":13},{"details":{"count":0,"maxCount":0},"source":"minecraft:barrel_4","slot":14},{"details":{"count":0,"maxCount":0},"source":"minecraft:barrel_4","slot":15},{"details":{"count":0,"maxCount":0},"source":"minecraft:barrel_4","slot":16},{"details":{"count":0,"maxCount":0},"source":"minecraft:barrel_4","slot":17},{"details":{"count":0,"maxCount":0},"source":"minecraft:barrel_4","slot":18},{"details":{"count":0,"maxCount":0},"source":"minecraft:barrel_4","slot":19},{"details":{"count":0,"maxCount":0},"source":"minecraft:barrel_4","slot":20},{"details":{"count":0,"maxCount":0},"source":"minecraft:barrel_4","slot":21},{"details":{"count":0,"maxCount":0},"source":"minecraft:barrel_4","slot":22},{"details":{"count":0,"maxCount":0},"source":"minecraft:barrel_4","slot":23},{"details":{"count":0,"maxCount":0},"source":"minecraft:barrel_4","slot":24},{"details":{"count":0,"maxCount":0},"source":"minecraft:barrel_4","slot":25},{"details":{"count":0,"maxCount":0},"source":"minecraft:barrel_4","slot":26},{"details":{"count":0,"maxCount":0},"source":"minecraft:barrel_4","slot":27},{"details":{"count":0,"maxCount":0},"source":"minecraft:barrel_5","slot":1},{"details":{"count":0,"maxCount":0},"source":"minecraft:barrel_5","slot":2},{"details":{"count":0,"maxCount":0},"source":"minecraft:barrel_5","slot":3},{"details":{"count":0,"maxCount":0},"source":"minecraft:barrel_5","slot":4},{"details":{"count":0,"maxCount":0},"source":"minecraft:barrel_5","slot":5},{"details":{"count":0,"maxCount":0},"source":"minecraft:barrel_5","slot":6},{"details":{"count":0,"maxCount":0},"source":"minecraft:barrel_5","slot":7},{"details":{"count":0,"maxCount":0},"source":"minecraft:barrel_5","slot":8},{"details":{"count":0,"maxCount":0},"source":"minecraft:barrel_5","slot":9},{"details":{"count":0,"maxCount":0},"source":"minecraft:barrel_5","slot":10},{"details":{"count":0,"maxCount":0},"source":"minecraft:barrel_5","slot":11},{"details":{"count":0,"maxCount":0},"source":"minecraft:barrel_5","slot":12},{"details":{"count":0,"maxCount":0},"source":"minecraft:barrel_5","slot":13},{"details":{"count":0,"maxCount":0},"source":"minecraft:barrel_5","slot":14},{"details":{"count":0,"maxCount":0},"source":"minecraft:barrel_5","slot":15},{"details":{"count":0,"maxCount":0},"source":"minecraft:barrel_5","slot":16},{"details":{"count":0,"maxCount":0},"source":"minecraft:barrel_5","slot":17},{"details":{"count":0,"maxCount":0},"source":"minecraft:barrel_5","slot":18},{"details":{"count":0,"maxCount":0},"source":"minecraft:barrel_5","slot":19},{"details":{"count":0,"maxCount":0},"source":"minecraft:barrel_5","slot":20},{"details":{"count":0,"maxCount":0},"source":"minecraft:barrel_5","slot":21},{"details":{"count":0,"maxCount":0},"source":"minecraft:barrel_5","slot":22},{"details":{"count":0,"maxCount":0},"source":"minecraft:barrel_5","slot":23},{"details":{"count":0,"maxCount":0},"source":"minecraft:barrel_5","slot":24},{"details":{"count":0,"maxCount":0},"source":"minecraft:barrel_5","slot":25},{"details":{"count":0,"maxCount":0},"source":"minecraft:barrel_5","slot":26},{"details":{"count":0,"maxCount":0},"source":"minecraft:barrel_5","slot":27},{"details":{"count":0,"maxCount":0},"source":"minecraft:barrel_8","slot":1},{"details":{"count":0,"maxCount":0},"source":"minecraft:barrel_8","slot":2},{"details":{"count":0,"maxCount":0},"source":"minecraft:barrel_8","slot":3},{"details":{"count":0,"maxCount":0},"source":"minecraft:barrel_8","slot":4},{"details":{"count":0,"maxCount":0},"source":"minecraft:barrel_8","slot":5},{"details":{"count":0,"maxCount":0},"source":"minecraft:barrel_8","slot":6},{"details":{"count":0,"maxCount":0},"source":"minecraft:barrel_8","slot":7},{"details":{"count":0,"maxCount":0},"source":"minecraft:barrel_8","slot":8},{"details":{"count":0,"maxCount":0},"source":"minecraft:barrel_8","slot":9},{"details":{"count":0,"maxCount":0},"source":"minecraft:barrel_8","slot":10},{"details":{"count":0,"maxCount":0},"source":"minecraft:barrel_8","slot":11},{"details":{"count":0,"maxCount":0},"source":"minecraft:barrel_8","slot":12},{"details":{"count":0,"maxCount":0},"source":"minecraft:barrel_8","slot":13},{"details":{"count":0,"maxCount":0},"source":"minecraft:barrel_8","slot":14},{"details":{"count":0,"maxCount":0},"source":"minecraft:barrel_8","slot":15},{"details":{"count":0,"maxCount":0},"source":"minecraft:barrel_8","slot":16},{"details":{"count":0,"maxCount":0},"source":"minecraft:barrel_8","slot":17},{"details":{"count":0,"maxCount":0},"source":"minecraft:barrel_8","slot":18},{"details":{"count":0,"maxCount":0},"source":"minecraft:barrel_8","slot":19},{"details":{"count":0,"maxCount":0},"source":"minecraft:barrel_8","slot":20},{"details":{"count":0,"maxCount":0},"source":"minecraft:barrel_8","slot":21},{"details":{"count":0,"maxCount":0},"source":"minecraft:barrel_8","slot":22},{"details":{"count":0,"maxCount":0},"source":"minecraft:barrel_8","slot":23},{"details":{"count":0,"maxCount":0},"source":"minecraft:barrel_8","slot":24},{"details":{"count":0,"maxCount":0},"source":"minecraft:barrel_8","slot":25},{"details":{"count":0,"maxCount":0},"source":"minecraft:barrel_8","slot":26},{"details":{"count":0,"maxCount":0},"source":"minecraft:barrel_8","slot":27},{"details":{"count":0,"maxCount":0},"source":"minecraft:barrel_9","slot":1},{"details":{"count":0,"maxCount":0},"source":"minecraft:barrel_9","slot":2},{"details":{"count":0,"maxCount":0},"source":"minecraft:barrel_9","slot":3},{"details":{"count":0,"maxCount":0},"source":"minecraft:barrel_9","slot":4},{"details":{"count":0,"maxCount":0},"source":"minecraft:barrel_9","slot":5},{"details":{"count":0,"maxCount":0},"source":"minecraft:barrel_9","slot":6},{"details":{"count":0,"maxCount":0},"source":"minecraft:barrel_9","slot":7},{"details":{"count":0,"maxCount":0},"source":"minecraft:barrel_9","slot":8},{"details":{"count":0,"maxCount":0},"source":"minecraft:barrel_9","slot":9},{"details":{"count":0,"maxCount":0},"source":"minecraft:barrel_9","slot":10},{"details":{"count":0,"maxCount":0},"source":"minecraft:barrel_9","slot":11},{"details":{"count":0,"maxCount":0},"source":"minecraft:barrel_9","slot":12},{"details":{"count":0,"maxCount":0},"source":"minecraft:barrel_9","slot":13},{"details":{"count":0,"maxCount":0},"source":"minecraft:barrel_9","slot":14},{"details":{"count":0,"maxCount":0},"source":"minecraft:barrel_9","slot":15},{"details":{"count":0,"maxCount":0},"source":"minecraft:barrel_9","slot":16},{"details":{"count":0,"maxCount":0},"source":"minecraft:barrel_9","slot":17},{"details":{"count":0,"maxCount":0},"source":"minecraft:barrel_9","slot":18},{"details":{"count":0,"maxCount":0},"source":"minecraft:barrel_9","slot":19},{"details":{"count":0,"maxCount":0},"source":"minecraft:barrel_9","slot":20},{"details":{"count":0,"maxCount":0},"source":"minecraft:barrel_9","slot":21},{"details":{"count":0,"maxCount":0},"source":"minecraft:barrel_9","slot":22},{"details":{"count":0,"maxCount":0},"source":"minecraft:barrel_9","slot":23},{"details":{"count":0,"maxCount":0},"source":"minecraft:barrel_9","slot":24},{"details":{"count":0,"maxCount":0},"source":"minecraft:barrel_9","slot":25},{"details":{"count":0,"maxCount":0},"source":"minecraft:barrel_9","slot":26},{"details":{"count":0,"maxCount":0},"source":"minecraft:barrel_9","slot":27},{"details":{"count":0,"maxCount":0},"source":"minecraft:barrel_2","slot":1},{"details":{"count":0,"maxCount":0},"source":"minecraft:barrel_2","slot":2},{"details":{"count":0,"maxCount":0},"source":"minecraft:barrel_2","slot":3},{"details":{"count":0,"maxCount":0},"source":"minecraft:barrel_2","slot":4},{"details":{"count":0,"maxCount":0},"source":"minecraft:barrel_2","slot":5},{"details":{"count":0,"maxCount":0},"source":"minecraft:barrel_2","slot":6},{"details":{"count":0,"maxCount":0},"source":"minecraft:barrel_2","slot":7},{"details":{"count":0,"maxCount":0},"source":"minecraft:barrel_2","slot":8},{"details":{"count":0,"maxCount":0},"source":"minecraft:barrel_2","slot":9},{"details":{"count":0,"maxCount":0},"source":"minecraft:barrel_2","slot":10},{"details":{"count":0,"maxCount":0},"source":"minecraft:barrel_2","slot":11},{"details":{"count":0,"maxCount":0},"source":"minecraft:barrel_2","slot":12},{"details":{"count":0,"maxCount":0},"source":"minecraft:barrel_2","slot":13},{"details":{"count":0,"maxCount":0},"source":"minecraft:barrel_2","slot":14},{"details":{"count":0,"maxCount":0},"source":"minecraft:barrel_2","slot":15},{"details":{"count":0,"maxCount":0},"source":"minecraft:barrel_2","slot":16},{"details":{"count":0,"maxCount":0},"source":"minecraft:barrel_2","slot":17},{"details":{"count":0,"maxCount":0},"source":"minecraft:barrel_2","slot":18},{"details":{"count":0,"maxCount":0},"source":"minecraft:barrel_2","slot":19},{"details":{"count":0,"maxCount":0},"source":"minecraft:barrel_2","slot":20},{"details":{"count":0,"maxCount":0},"source":"minecraft:barrel_2","slot":21},{"details":{"count":0,"maxCount":0},"source":"minecraft:barrel_2","slot":22},{"details":{"count":0,"maxCount":0},"source":"minecraft:barrel_2","slot":23},{"details":{"count":0,"maxCount":0},"source":"minecraft:barrel_2","slot":24},{"details":{"count":0,"maxCount":0},"source":"minecraft:barrel_2","slot":25},{"details":{"count":0,"maxCount":0},"source":"minecraft:barrel_2","slot":26},{"details":{"count":0,"maxCount":0},"source":"minecraft:barrel_2","slot":27},{"details":{"count":0,"maxCount":0},"source":"minecraft:barrel_3","slot":1},{"details":{"count":0,"maxCount":0},"source":"minecraft:barrel_3","slot":2},{"details":{"count":0,"maxCount":0},"source":"minecraft:barrel_3","slot":3},{"details":{"count":0,"maxCount":0},"source":"minecraft:barrel_3","slot":4},{"details":{"count":0,"maxCount":0},"source":"minecraft:barrel_3","slot":5},{"details":{"count":0,"maxCount":0},"source":"minecraft:barrel_3","slot":6},{"details":{"count":0,"maxCount":0},"source":"minecraft:barrel_3","slot":7},{"details":{"count":0,"maxCount":0},"source":"minecraft:barrel_3","slot":8},{"details":{"count":0,"maxCount":0},"source":"minecraft:barrel_3","slot":9},{"details":{"count":0,"maxCount":0},"source":"minecraft:barrel_3","slot":10},{"details":{"count":0,"maxCount":0},"source":"minecraft:barrel_3","slot":11},{"details":{"count":0,"maxCount":0},"source":"minecraft:barrel_3","slot":12},{"details":{"count":0,"maxCount":0},"source":"minecraft:barrel_3","slot":13},{"details":{"count":0,"maxCount":0},"source":"minecraft:barrel_3","slot":14},{"details":{"count":0,"maxCount":0},"source":"minecraft:barrel_3","slot":15},{"details":{"count":0,"maxCount":0},"source":"minecraft:barrel_3","slot":16},{"details":{"count":0,"maxCount":0},"source":"minecraft:barrel_3","slot":17},{"details":{"count":0,"maxCount":0},"source":"minecraft:barrel_3","slot":18},{"details":{"count":0,"maxCount":0},"source":"minecraft:barrel_3","slot":19},{"details":{"count":0,"maxCount":0},"source":"minecraft:barrel_3","slot":20},{"details":{"count":0,"maxCount":0},"source":"minecraft:barrel_3","slot":21},{"details":{"count":0,"maxCount":0},"source":"minecraft:barrel_3","slot":22},{"details":{"count":0,"maxCount":0},"source":"minecraft:barrel_3","slot":23},{"details":{"count":0,"maxCount":0},"source":"minecraft:barrel_3","slot":24},{"details":{"count":0,"maxCount":0},"source":"minecraft:barrel_3","slot":25},{"details":{"count":0,"maxCount":0},"source":"minecraft:barrel_3","slot":26},{"details":{"count":0,"maxCount":0},"source":"minecraft:barrel_3","slot":27},{"details":{"count":0,"maxCount":0},"source":"minecraft:barrel_0","slot":1},{"details":{"count":0,"maxCount":0},"source":"minecraft:barrel_0","slot":2},{"details":{"count":0,"maxCount":0},"source":"minecraft:barrel_0","slot":3},{"details":{"count":0,"maxCount":0},"source":"minecraft:barrel_0","slot":4},{"details":{"count":0,"maxCount":0},"source":"minecraft:barrel_0","slot":5},{"details":{"count":0,"maxCount":0},"source":"minecraft:barrel_0","slot":6},{"details":{"count":0,"maxCount":0},"source":"minecraft:barrel_0","slot":7},{"details":{"count":0,"maxCount":0},"source":"minecraft:barrel_0","slot":8},{"details":{"count":0,"maxCount":0},"source":"minecraft:barrel_0","slot":9},{"details":{"count":0,"maxCount":0},"source":"minecraft:barrel_0","slot":10},{"details":{"count":0,"maxCount":0},"source":"minecraft:barrel_0","slot":11},{"details":{"count":0,"maxCount":0},"source":"minecraft:barrel_0","slot":12},{"details":{"count":0,"maxCount":0},"source":"minecraft:barrel_0","slot":13},{"details":{"count":0,"maxCount":0},"source":"minecraft:barrel_0","slot":14},{"details":{"count":0,"maxCount":0},"source":"minecraft:barrel_0","slot":15},{"details":{"count":0,"maxCount":0},"source":"minecraft:barrel_0","slot":16},{"details":{"count":0,"maxCount":0},"source":"minecraft:barrel_0","slot":17},{"details":{"count":0,"maxCount":0},"source":"minecraft:barrel_0","slot":18},{"details":{"count":0,"maxCount":0},"source":"minecraft:barrel_0","slot":19},{"details":{"count":0,"maxCount":0},"source":"minecraft:barrel_0","slot":20},{"details":{"count":0,"maxCount":0},"source":"minecraft:barrel_0","slot":21},{"details":{"count":0,"maxCount":0},"source":"minecraft:barrel_0","slot":22},{"details":{"count":0,"maxCount":0},"source":"minecraft:barrel_0","slot":23},{"details":{"count":0,"maxCount":0},"source":"minecraft:barrel_0","slot":24},{"details":{"count":0,"maxCount":0},"source":"minecraft:barrel_0","slot":25},{"details":{"count":0,"maxCount":0},"source":"minecraft:barrel_0","slot":26},{"details":{"count":0,"maxCount":0},"source":"minecraft:barrel_0","slot":27},{"details":{"count":0,"maxCount":0},"source":"minecraft:barrel_1","slot":1},{"details":{"count":0,"maxCount":0},"source":"minecraft:barrel_1","slot":2},{"details":{"count":0,"maxCount":0},"source":"minecraft:barrel_1","slot":3},{"details":{"count":0,"maxCount":0},"source":"minecraft:barrel_1","slot":4},{"details":{"count":0,"maxCount":0},"source":"minecraft:barrel_1","slot":5},{"details":{"count":0,"maxCount":0},"source":"minecraft:barrel_1","slot":6},{"details":{"count":0,"maxCount":0},"source":"minecraft:barrel_1","slot":7},{"details":{"count":0,"maxCount":0},"source":"minecraft:barrel_1","slot":8},{"details":{"count":0,"maxCount":0},"source":"minecraft:barrel_1","slot":9},{"details":{"count":0,"maxCount":0},"source":"minecraft:barrel_1","slot":10},{"details":{"count":0,"maxCount":0},"source":"minecraft:barrel_1","slot":11},{"details":{"count":0,"maxCount":0},"source":"minecraft:barrel_1","slot":12},{"details":{"count":0,"maxCount":0},"source":"minecraft:barrel_1","slot":13},{"details":{"count":0,"maxCount":0},"source":"minecraft:barrel_1","slot":14},{"details":{"count":0,"maxCount":0},"source":"minecraft:barrel_1","slot":15},{"details":{"count":0,"maxCount":0},"source":"minecraft:barrel_1","slot":16},{"details":{"count":0,"maxCount":0},"source":"minecraft:barrel_1","slot":17},{"details":{"count":0,"maxCount":0},"source":"minecraft:barrel_1","slot":18},{"details":{"count":0,"maxCount":0},"source":"minecraft:barrel_1","slot":19},{"details":{"count":0,"maxCount":0},"source":"minecraft:barrel_1","slot":20},{"details":{"count":0,"maxCount":0},"source":"minecraft:barrel_1","slot":21},{"details":{"count":0,"maxCount":0},"source":"minecraft:barrel_1","slot":22},{"details":{"count":0,"maxCount":0},"source":"minecraft:barrel_1","slot":23},{"details":{"count":0,"maxCount":0},"source":"minecraft:barrel_1","slot":24},{"details":{"count":0,"maxCount":0},"source":"minecraft:barrel_1","slot":25},{"details":{"count":0,"maxCount":0},"source":"minecraft:barrel_1","slot":26},{"details":{"count":0,"maxCount":0},"source":"minecraft:barrel_1","slot":27},{"details":{"count":0,"maxCount":0},"source":"minecraft:barrel_10","slot":1},{"details":{"count":0,"maxCount":0},"source":"minecraft:barrel_10","slot":2},{"details":{"count":0,"maxCount":0},"source":"minecraft:barrel_10","slot":3},{"details":{"count":0,"maxCount":0},"source":"minecraft:barrel_10","slot":4},{"details":{"count":0,"maxCount":0},"source":"minecraft:barrel_10","slot":5},{"details":{"count":0,"maxCount":0},"source":"minecraft:barrel_10","slot":6},{"details":{"count":0,"maxCount":0},"source":"minecraft:barrel_10","slot":7},{"details":{"count":0,"maxCount":0},"source":"minecraft:barrel_10","slot":8},{"details":{"count":0,"maxCount":0},"source":"minecraft:barrel_10","slot":9},{"details":{"count":0,"maxCount":0},"source":"minecraft:barrel_10","slot":10},{"details":{"count":0,"maxCount":0},"source":"minecraft:barrel_10","slot":11},{"details":{"count":0,"maxCount":0},"source":"minecraft:barrel_10","slot":12},{"details":{"count":0,"maxCount":0},"source":"minecraft:barrel_10","slot":13},{"details":{"count":0,"maxCount":0},"source":"minecraft:barrel_10","slot":14},{"details":{"count":0,"maxCount":0},"source":"minecraft:barrel_10","slot":15},{"details":{"count":0,"maxCount":0},"source":"minecraft:barrel_10","slot":16},{"details":{"count":0,"maxCount":0},"source":"minecraft:barrel_10","slot":17},{"details":{"count":0,"maxCount":0},"source":"minecraft:barrel_10","slot":18},{"details":{"count":0,"maxCount":0},"source":"minecraft:barrel_10","slot":19},{"details":{"count":0,"maxCount":0},"source":"minecraft:barrel_10","slot":20},{"details":{"count":0,"maxCount":0},"source":"minecraft:barrel_10","slot":21},{"details":{"count":0,"maxCount":0},"source":"minecraft:barrel_10","slot":22},{"details":{"count":0,"maxCount":0},"source":"minecraft:barrel_10","slot":23},{"details":{"count":0,"maxCount":0},"source":"minecraft:barrel_10","slot":24},{"details":{"count":0,"maxCount":0},"source":"minecraft:barrel_10","slot":25},{"details":{"count":0,"maxCount":0},"source":"minecraft:barrel_10","slot":26},{"details":{"count":0,"maxCount":0},"source":"minecraft:barrel_10","slot":27},{"details":{"count":0,"maxCount":0},"source":"minecraft:barrel_11","slot":1},{"details":{"count":0,"maxCount":0},"source":"minecraft:barrel_11","slot":2},{"details":{"count":0,"maxCount":0},"source":"minecraft:barrel_11","slot":3},{"details":{"count":0,"maxCount":0},"source":"minecraft:barrel_11","slot":4},{"details":{"count":0,"maxCount":0},"source":"minecraft:barrel_11","slot":5},{"details":{"count":0,"maxCount":0},"source":"minecraft:barrel_11","slot":6},{"details":{"count":0,"maxCount":0},"source":"minecraft:barrel_11","slot":7},{"details":{"count":0,"maxCount":0},"source":"minecraft:barrel_11","slot":8},{"details":{"count":0,"maxCount":0},"source":"minecraft:barrel_11","slot":9},{"details":{"count":0,"maxCount":0},"source":"minecraft:barrel_11","slot":10},{"details":{"count":0,"maxCount":0},"source":"minecraft:barrel_11","slot":11},{"details":{"count":0,"maxCount":0},"source":"minecraft:barrel_11","slot":12},{"details":{"count":0,"maxCount":0},"source":"minecraft:barrel_11","slot":13},{"details":{"count":0,"maxCount":0},"source":"minecraft:barrel_11","slot":14},{"details":{"count":0,"maxCount":0},"source":"minecraft:barrel_11","slot":15},{"details":{"count":0,"maxCount":0},"source":"minecraft:barrel_11","slot":16},{"details":{"count":0,"maxCount":0},"source":"minecraft:barrel_11","slot":17},{"details":{"count":0,"maxCount":0},"source":"minecraft:barrel_11","slot":18},{"details":{"count":0,"maxCount":0},"source":"minecraft:barrel_11","slot":19},{"details":{"count":0,"maxCount":0},"source":"minecraft:barrel_11","slot":20},{"details":{"count":0,"maxCount":0},"source":"minecraft:barrel_11","slot":21},{"details":{"count":0,"maxCount":0},"source":"minecraft:barrel_11","slot":22},{"details":{"count":0,"maxCount":0},"source":"minecraft:barrel_11","slot":23},{"details":{"count":0,"maxCount":0},"source":"minecraft:barrel_11","slot":24},{"details":{"count":0,"maxCount":0},"source":"minecraft:barrel_11","slot":25},{"details":{"count":0,"maxCount":0},"source":"minecraft:barrel_11","slot":26},{"details":{"count":0,"maxCount":0},"source":"minecraft:barrel_11","slot":27}]},"minecraft:gray_wool":{"nbt":{},"stacks":[{"details":{"tags":{"chipped:gray_wool":true,"minecraft:wool":true,"c:dyed":true,"c:dyed/gray":true,"minecraft:dampens_vibrations":true},"mapColour":5000268,"name":"minecraft:gray_wool","itemGroups":[{"id":"minecraft:colored_blocks","displayName":"Colored Blocks"}],"count":64,"mapColor":5000268,"maxCount":64,"displayName":"Gray Wool"},"source":"minecraft:barrel_6","slot":4}]},"createdeco:iron_coinstack":{"nbt":{},"stacks":[{"details":{"name":"createdeco:iron_coinstack","itemGroups":[{"id":"createdeco:props_tab","displayName":"Create Deco Props"}],"tags":{},"count":41,"maxCount":64,"displayName":"Iron Coin Stack"},"source":"minecraft:barrel_6","slot":2}]}}